hash_controller/__init__.py
hash_controller/aws_manager.py
hash_controller/main.py
hash_controller/settings.py
hash_controller/database/__init__.py
hash_controller/database/database_interface.py
hash_controller/database/db_credentials.py
hash_controller/database/db_factory.py
hash_controller/database/dynamodb.py
hash_controller/database/mongodb.py
hash_controller/database/postgresql.py
tests/__init__.py
tests/test_mongo.py
hash_controller-1.1.7.dist-info/METADATA
hash_controller-1.1.7.dist-info/WHEEL
hash_controller-1.1.7.dist-info/top_level.txt
hash_controller-1.1.7.dist-info/RECORD
