Metadata-Version: 2.1
Name: hash-controller
Version: 1.1.7
Summary: File controller via hash
Home-page: https://github.com/edmachina/hash_controller
Author: Ezequiel Marcel
Author-email: ezequiel.marcel@edmachina.com
Keywords: pip,hash,controller
Requires-Python: >=3.9
Requires-Dist: pymongo >=4.5.0
Requires-Dist: boto3
Requires-Dist: psycopg2-binary
Requires-Dist: python-dotenv
Requires-Dist: pydantic <2.0.0,>=1.9.0
Requires-Dist: sshtunnel
